notabot/__init__.py
notabot/notarize/__init__.py
notabot/notarize/__main__.py
notabot/sign/__init__.py
notabot/sign/__main__.py
notabot-2.0.2.dist-info/LICENSE
notabot-2.0.2.dist-info/METADATA
notabot-2.0.2.dist-info/WHEEL
notabot-2.0.2.dist-info/top_level.txt
notabot-2.0.2.dist-info/RECORD
