Metadata-Version: 2.1
Name: notabot
Version: 2.0.2
Summary: Automated codesigning and notarization of a macOS app.
Author-email: Marc Culler <culler@users.noreply.github.com>, "Nathan M. Dunfield" <nathan@dunfield.info>, Matthias Görner <enischte@gmail.com>
Maintainer-email: Marc Culler <culler@users.noreply.github.com>, "Nathan M. Dunfield" <nathan@dunfield.info>, Matthias Görner <enischte@gmail.com>
Project-URL: Homepage, https://github.com/3-manifolds/notabot
Project-URL: Bug Tracker, https://github.com/3-manifolds/notabot/issues
Keywords: app,codesign,notarize
Classifier: Development Status :: 5 - Production/Stable
Classifier: Intended Audience :: Developers
Classifier: License :: OSI Approved :: GNU General Public License v2 or later (GPLv2+)
Classifier: Operating System :: MacOS
Classifier: Programming Language :: Python
Classifier: Topic :: Software Development
Requires-Python: >=3.8
License-File: LICENSE
